MANIFEST.in
README.txt
conf.py
index.rst
sPickle.rst
setup.cfg
setup.py
sPickle/__init__.py
sPickle/_sPickle.py
sPickle.egg-info/PKG-INFO
sPickle.egg-info/SOURCES.txt
sPickle.egg-info/dependency_links.txt
sPickle.egg-info/top_level.txt
sPickle/examples/checkpointing.py
sPickle/examples/example1.py
sPickle/examples/example2.py
sPickle/examples/rpyc_over_ssh.py
sPickle/test/__init__.py
sPickle/test/mod_with_wrong_name.py
sPickle/test/testSPickle.py
sPickle/test/wf_modul2.py
sPickle/test/wf_module.py