Metadata-Version: 1.1
Name: sPickle
Version: 0.1.9
Summary: Extended Pickler with special support for Stackless Python
Home-page: http://pypi.python.org/pypi/sPickle
Author: Anselm Kruis
Author-email: a.kruis@science-computing.de
License: Apache Software License
Keywords: pickling sPickle pickle stackless
Platform: any
Classifier: License :: OSI Approved :: Apache Software License
Classifier: Programming Language :: Python
Classifier: Programming Language :: Python :: 2.7
Classifier: Environment :: Other Environment
Classifier: Operating System :: OS Independent
Classifier: Development Status :: 4 - Beta
Classifier: Intended Audience :: Developers
Classifier: Topic :: Software Development :: Libraries :: Python Modules
